{"artifacts":{"00000001":{"path":"ad1fcd34af49dfba0662f96901304e9d.pdf","url":"","type":"pdf","total_video":"","video_dir":"sdsdsccc\/video\/","window":"newtab\/iframe","title":"localhost_test","description":"","tags":"","size":"0.08 MB","createdTime":"1455779334"},"00000002":{"path":"95bfe19ebf89fce7b21fd9c8b6635eed.mp4","url":"","type":"video","total_video":"","video_dir":"sdsdsccc\/video\/","window":"newtab\/iframe","title":"sample","description":"","tags":"","size":"0.09 MB","createdTime":"1455779347"}}}